AUTHORS.txt
CHANGES.txt
CONTRIBUTORS.txt
LICENSE.txt
MANIFEST.in
README.txt
setup.cfg
setup.py
lib/Yamlog.egg-info/PKG-INFO
lib/Yamlog.egg-info/SOURCES.txt
lib/Yamlog.egg-info/dependency_links.txt
lib/Yamlog.egg-info/top_level.txt
lib/Yamlog.egg-info/zip-safe
lib/yamlog/__init__.py
lib/yamlog/exception.py
lib/yamlog/logger.py
test/__init__.py
test/test.py