Metadata-Version: 1.0
Name: Yamlog
Version: 0.9
Summary: Logging in YAML format
Home-page: http://github.com/kless/Yamlog
Author: Jonas Melian
Author-email: jonas@mailup.net
License: UNKNOWN
Keywords: log logging
Platform: UNKNOWN
Classifier: Development Status :: 4 - Beta
Classifier: Intended Audience :: Developers
Classifier: License :: OSI Approved :: ISC License (ISCL)
Classifier: Natural Language :: English
Classifier: Operating System :: POSIX
Classifier: Programming Language :: Python :: 2.6
Classifier: Topic :: System :: Logging
